upwork_scrap/__init__.py
upwork_scrap/search.py
upwork_scrap-4.0.0.dist-info/LICENSE
upwork_scrap-4.0.0.dist-info/METADATA
upwork_scrap-4.0.0.dist-info/WHEEL
upwork_scrap-4.0.0.dist-info/top_level.txt
upwork_scrap-4.0.0.dist-info/RECORD
