Metadata-Version: 2.1
Name: upwork-scrap
Version: 4.0.0
Summary: automate upwork
Author-email: <oussema.benhassena@horizon-tech.tn>
Keywords: python,video,stream,video stream,camera stream,sockets
Classifier: Development Status :: 1 - Planning
Classifier: Intended Audience :: Developers
Classifier: Programming Language :: Python :: 3
Classifier: Operating System :: Unix
Classifier: Operating System :: MacOS :: MacOS X
Classifier: Operating System :: Microsoft :: Windows
License-File: LICENSE
Requires-Dist: selenium
Requires-Dist: gpt4free
